limonade_plot_utils/__init__.py
limonade_plot_utils/create_plots.py
limonade_plot_utils/fix_data.py
limonade_plot_utils/read_hist_data.py
limonade_plot_utils/read_list_data.py
limonade_plot_utils/utils.py
limonade_plot_utils-0.8.1.dist-info/METADATA
limonade_plot_utils-0.8.1.dist-info/WHEEL
limonade_plot_utils-0.8.1.dist-info/entry_points.txt
limonade_plot_utils-0.8.1.dist-info/top_level.txt
limonade_plot_utils-0.8.1.dist-info/RECORD
