Metadata-Version: 2.1
Name: limonade-plot-utils
Version: 0.8.1
Summary: Utilities and plot scripts for Limonade.
Home-page: https://gitlab.com/tehilden/limonade-plot-utils.git
Author: Timo Hilden
Author-email: timo.hilden@helsinki.fi
Project-URL: Bug Tracker, https://gitlab.com/tehilden/limonade-plot-utils
Classifier: Programming Language :: Python :: 3
Classifier: License :: OSI Approved :: MIT License
Classifier: Operating System :: OS Independent
Classifier: Development Status :: 4 - Beta
Requires-Python: >=3.7
Requires-Dist: matplotlib
Requires-Dist: limonade >=0.9.1
